origo/devportal/poctools/__init__.py
origo/devportal/poctools/env.py
origo/devportal/poctools/job.py
origo/devportal/poctools/models/__init__.py
origo/devportal/poctools/models/api.py
origo/devportal/poctools/models/dataset.py
origo/devportal/poctools/models/source.py
origo/devportal/poctools/models/visibility.py
tests/dataset_test.py
origo_devportal_poctools-0.0.6.dist-info/METADATA
origo_devportal_poctools-0.0.6.dist-info/WHEEL
origo_devportal_poctools-0.0.6.dist-info/top_level.txt
origo_devportal_poctools-0.0.6.dist-info/RECORD
