Metadata-Version: 2.1
Name: origo-devportal-poctools
Version: 0.0.6
Summary: A set of tools and models used by all parts of the harvest poc
Home-page: UNKNOWN
Author: Oslo Origo
Author-email: developerportal@oslo.kommune.no
License: https://mit-license.org/
Project-URL: Bug Tracker, https://github.com/oslokommune/devportal-harvest-poc/issues
Project-URL: Source Code, https://github.com/oslokommune/devportal-harvest-poc
Platform: UNKNOWN
Requires-Dist: pyyaml (==5.3.1)
